tests/_gen_figures/__init__.py
tests/_gen_figures/_utils.py
tests/_gen_figures/test_plots.py
tests/backend/__init__.py
tests/backend/test_benchmark.py
tests/backend/test_model.py
tests/backend/test_tools.py
tests/cli/__init__.py
tests/cli/test__shell_complete.py
tests/cli/test__to_migrate.py
tests/cli/test_batch.py
tests/cli/test_config.py
tests/cli/test_models.py
tests/cli/test_projects.py
tests/cli/test_run_and_eval.py
tests/cli/test_test.py
tests/eval/__init__.py
tests/eval/test_containers.py
tests/eval/test_datamanager.py
tests/eval/test_groups.py
tests/eval/test_plot_utils.py
tests/eval/test_plotting.py
utopya/__init__.py
utopya/_cluster.py
utopya/_import_tools.py
utopya/_logging.py
utopya/_resources.py
utopya/_signal.py
utopya/_yaml.py
utopya/batch.py
utopya/cfg.py
utopya/exceptions.py
utopya/model.py
utopya/multiverse.py
utopya/parameter.py
utopya/plotting.py
utopya/project_registry.py
utopya/reporter.py
utopya/stop_conditions.py
utopya/task.py
utopya/testtools.py
utopya/tools.py
utopya/workermanager.py
utopya/yaml.py
utopya/_yaml_registry/__init__.py
utopya/_yaml_registry/entry.py
utopya/_yaml_registry/registry.py
utopya/cfg/base_cfg.yml
utopya/cfg/base_plots.yml
utopya/cfg/btm_cfg.yml
utopya/cfg/user_cfg_header.yml
utopya/eval/__init__.py
utopya/eval/_plot_func_resolver.py
utopya/eval/containers.py
utopya/eval/data_ops.py
utopya/eval/datamanager.py
utopya/eval/groups.py
utopya/eval/plotcreators.py
utopya/eval/plothelper.py
utopya/eval/plotmanager.py
utopya/eval/transform.py
utopya/eval/plots/__init__.py
utopya/eval/plots/_attractor.py
utopya/eval/plots/_graph.py
utopya/eval/plots/_mpl.py
utopya/eval/plots/_utils.py
utopya/eval/plots/abm.py
utopya/eval/plots/attractor.py
utopya/eval/plots/ca.py
utopya/eval/plots/distributions.py
utopya/eval/plots/graph.py
utopya/eval/plots/time_series.py
utopya/model_registry/__init__.py
utopya/model_registry/_registration.py
utopya/model_registry/entry.py
utopya/model_registry/info_bundle.py
utopya-1.3.11.dist-info/licenses/COPYING
utopya-1.3.11.dist-info/licenses/COPYING.LESSER
utopya-1.3.11.dist-info/METADATA
utopya-1.3.11.dist-info/WHEEL
utopya-1.3.11.dist-info/entry_points.txt
utopya-1.3.11.dist-info/top_level.txt
utopya-1.3.11.dist-info/RECORD
