Metadata-Version: 2.4
Name: utopya
Version: 1.3.11
Summary: A simulation management and evaluation framework
Home-page: https://gitlab.com/utopia-project/utopya
Author: utopya developers
Author-email: Yunus Sevinchan <yunus.sevinchan@hu-berlin.de>
Classifier: Programming Language :: Python :: 3.9
Classifier: Programming Language :: Python :: 3.10
Classifier: Programming Language :: Python :: 3.11
Classifier: Programming Language :: Python :: 3.12
Classifier: Programming Language :: Python :: 3.13
Classifier: Programming Language :: Python :: 3.14
Classifier: License :: OSI Approved :: GNU Lesser General Public License v3 or later (LGPLv3+)
Classifier: Development Status :: 5 - Production/Stable
Classifier: Intended Audience :: Developers
Classifier: Intended Audience :: Science/Research
Classifier: Topic :: Utilities
Classifier: Topic :: Scientific/Engineering
License-File: COPYING
License-File: COPYING.LESSER
Requires-Dist: numpy
Requires-Dist: scipy
Requires-Dist: matplotlib
Requires-Dist: seaborn
Requires-Dist: ruamel.yaml
Requires-Dist: coloredlogs
Requires-Dist: colorama
Requires-Dist: click
Requires-Dist: pydantic>=2.0
Requires-Dist: python-git-info
Requires-Dist: yayaml>=0.2.4
Requires-Dist: paramspace>=2.8.2
Requires-Dist: dantro>=0.21.1
Provides-Extra: test
Requires-Dist: pytest; extra == "test"
Requires-Dist: pytest-cov; extra == "test"
Requires-Dist: pytest-order; extra == "test"
Requires-Dist: pre-commit; extra == "test"
Provides-Extra: doc
Requires-Dist: sphinx>=5.3; extra == "doc"
Requires-Dist: sphinx-book-theme; extra == "doc"
Requires-Dist: sphinx-togglebutton; extra == "doc"
Requires-Dist: ipython>=7.0; extra == "doc"
Requires-Dist: myst-parser[linkify]; extra == "doc"
Requires-Dist: sphinx-click; extra == "doc"
Requires-Dist: pytest; extra == "doc"
Provides-Extra: opt
Requires-Dist: networkx; extra == "opt"
Requires-Dist: pygraphviz; extra == "opt"
Provides-Extra: dev
Requires-Dist: pytest; extra == "dev"
Requires-Dist: pytest-cov; extra == "dev"
Requires-Dist: pytest-order; extra == "dev"
Requires-Dist: pre-commit; extra == "dev"
Requires-Dist: sphinx>=5.3; extra == "dev"
Requires-Dist: sphinx-book-theme; extra == "dev"
Requires-Dist: sphinx-togglebutton; extra == "dev"
Requires-Dist: ipython>=7.0; extra == "dev"
Requires-Dist: myst-parser[linkify]; extra == "dev"
Requires-Dist: sphinx-click; extra == "dev"
Requires-Dist: pytest; extra == "dev"
Requires-Dist: networkx; extra == "dev"
Requires-Dist: pygraphviz; extra == "dev"
Dynamic: author
Dynamic: author-email
Dynamic: classifier
Dynamic: description
Dynamic: home-page
Dynamic: license-file
Dynamic: provides-extra
Dynamic: requires-dist
Dynamic: summary
